[
    {
        "number": "09",
        "title": "Podstawy Symfony",
        "logo-img": "09-phpsymfony.png",
        "date": "2016-11-26",
        "date-date-month_long": "26 listopada",
        "date-year": "bieżący rok :)",
        "description-short": "„Podstawy Symfony” to warsztaty przeznaczone dla osób zaczynających przygodę z Symfony. Piguła teorii i spora dawka praktyki gwarantowane.",
        "description-long-html": "<p>W trakcie warsztatów chcemy pokazać jak można zacząć pisanie aplikacji w Symfony. Wykorzystamy wieloletnie doświadczenie w pracy przy dużej skali w sporym zespole, nabytą tam wiedzę oraz dobre praktyki. Opowiemy jak pisać dobry i wydajny, ale jednocześnie prosty i zrozumiały kod.</p><p>Nie zanudzimy nudną teorią! Po krótkim wstępie i przedstawieniu frameworka przejdziemy do budowania aplikacji. Przejdziemy przez wszystkie podstawowe elementy, a jak wystarczy nam czasu dodamy nieco zaawansowanej wiedzy ;-). Postaramy się tak przygotować materiały, żeby każdy mógł spokojnie wypróbować wszystko czy to na warsztatach czy po - jako wprawkę.</p><p>Warsztaty kierujemy do osób, które znają przynajmniej podstawy PHP, wykorzystują inne frameworki i chcą zobaczyć „o co tyle szumu” oraz osoby, które zaczęły już pracę z Symfony i chcą złapać nieco więcej praktycznej wiedzy.</p>",
        "speakers": [
            {
                "speaker-name": "Dominik Gawryszewski",
                "speaker-img": "dominik-gawryszewski.png",
                "speaker-link": "dominik-gawryszewski",
                "speaker-contact": [
                    {
                        "url": "https://twitter.com/domen1806",
                        "direction": "right",
                        "icon": "twitter"
                    }
                ],
                "speaker-short-description-html": "<p>Swoją przygodę z programowaniem rozpoczął od razu od PHP i framework’a Symfony2. Jego motto życiowe brzmi: zawsze możesz zrobić coś lepiej.</p>"                
            },
            {
                "speaker-name": "Krzysztof Jończyk",
                "speaker-img": "krzysztof-jonczyk.png",
                "speaker-link": "krzysztof-jonczyk",
                "speaker-contact": [
                    {
                        "url": "http://jonczyk.me",
                        "direction": "left",
                        "icon": "globe"
                    },
                    {
                        "url": "https://twitter.com/krzychjonczyk",
                        "direction": "right",
                        "icon": "twitter"
                    }
                ],
                "speaker-short-description-html": "<p>Od ponad 7 lat związany z szeroko pojętym web developmentem. Fanatyk czystego kodu. Freak na punkcie produktywności i samorozwoju.</p>"                
            }
        ],
        "venue-city": "Warszawa",
        "venue-address": "mBank, Królewska 14",
        "venue-address-google-maps": "mBank, Królewska 14, Warsaw, Poland",
        "seat-count": "25",
        "agenta-html": "<p>Godziny 10:00 - 15:00</p><p><ol><li>wstęp do Symfony</li><li>instalacja Symfony</li><li>kontroler/model/widok</li><li>struktura bazy banych, Doctrine</li><li>logowanie, FOSUserBundle</li><li>CRUD + formularze</li><li>wykorzystanie serwisów</li><li>————— na 6</li><li>eventy</li><li>komendy</li></ol><h2>Wymagania od uczestników</h2><ul><li>podstawowa znajomość PHP</li><li>PhpStorm (jest 30-dniowy trial https://www.jetbrains.com/phpstorm/download/)</li><li>zainstalowany PHP w wersji co najmniej 5.6 z zainstalowanym mod_sqlite3</li><li>zainstalowany composer (https://getcomposer.org/)</li><li>zainstalowany Git (https://git-scm.com/book/en/v2/Getting-Started-Installing-Git)</li></ul>",
        "sponsor-name": "mBank",
        "sponsor-url": "http://www.mbank.pl",
        "sponsors": [
            {
                "name": "mBank",
                "url": "http://www.mbank.pl",
                "img": "/images/sponsors/mbank-logo.png"
            },
            {
                "name": "JetBrains",
                "url": "http://jetbrains.com",
                "img": "/images/sponsors/jetbrains-logo.png"
            }
        ],
        "meetup-register-url": "http://www.meetup.com/devWarsztaty/"
    }
]